{"abstract": "This week\u2019s Tech Talk podcast includes Jenna Wortham on alternatives to Facebook and robots in the operating room.", "web_url": "https://bits.blogs.nytimes.com/2010/06/02/tech-talk-podcast-robot-surgery/", "snippet": "This week\u2019s Tech Talk podcast includes Jenna Wortham on alternatives to Facebook and robots in the operating room.", "lead_paragraph": "In this week\u2019s New York Times Tech Talk podcast, Bettina Edelstein finds out about some fledgling alternatives to Facebook from Jenna Wortham, a Times technology reporter who covers digital culture and the Web. These social networking upstarts have emerged at a time of widespread concern over the privacy policies of Facebook, and Ms. Wortham says their creators see a potential opportunity, offering different ways of sharing information.", "source": "The New York Times", "multimedia": [], "headline": {"main": "Tech Talk Podcast: Robot Surgery", "kicker": "Bits", "content_kicker": null, "print_headline": "", "name": null, "seo": null, "sub": null}, "keywords": [], "pub_date": "2010-06-02T21:01:22+0000", "document_type": "article", "news_desk": "Business", "section_name": "Technology", "byline": {"original": "By The New York Times", "person": [], "organization": "The New York Times"}, "type_of_material": "", "_id": "nyt://article/a50d9606-9e57-57a5-aa37-88d1cb16d6d3", "word_count": 287, "uri": "nyt://article/a50d9606-9e57-57a5-aa37-88d1cb16d6d3"}