{"abstract": "Readers respond to \u201cA More Efficient World That People May Not Want\u201d (July 1).", "web_url": "https://www.nytimes.com/2016/07/10/business/protectionism-a-fleeting-promise.html", "snippet": "Readers respond to \u201cA More Efficient World That People May Not Want\u201d (July 1).", "lead_paragraph": "To the Editor:", "print_section": "BU", "print_page": "6", "source": "The New York Times", "multimedia": [], "headline": {"main": "Protectionism: A Fleeting Promise", "kicker": "Letters", "content_kicker": null, "print_headline": "", "name": null, "seo": null, "sub": null}, "keywords": [{"name": "subject", "value": "Letters", "rank": 1, "major": "N"}, {"name": "subject", "value": "Presidential Election of 2016", "rank": 2, "major": "N"}, {"name": "subject", "value": "Great Britain Withdrawal from EU (Brexit)", "rank": 3, "major": "N"}, {"name": "persons", "value": "Trump, Donald J", "rank": 4, "major": "N"}], "pub_date": "2016-07-09T18:33:57+0000", "document_type": "article", "news_desk": "SundayBusiness", "section_name": "Business Day", "byline": {"original": "By The New York Times", "person": [], "organization": "The New York Times"}, "type_of_material": "News", "_id": "nyt://article/bd1b477b-9d9f-55c1-abbb-99d61857b646", "word_count": 146, "uri": "nyt://article/bd1b477b-9d9f-55c1-abbb-99d61857b646"}