{"abstract": "Gazprom, the Russian state-run gas company, on Wednesday completed the purchase of its controlling share in the Sakhalin-2 oil and gas project, buying half the stakes owned by Royal Dutch Shell, Mitsui and Mitsubishi for $7.45 billion.", "web_url": "https://dealbook.nytimes.com/2007/04/19/gazprom-takes-control-of-sakhalin-oil-project/", "snippet": "", "lead_paragraph": "Gazprom, the Russian state-run gas company, on Wednesday completed the purchase of its controlling share in the Sakhalin-2 oil and gas project, buying half the stakes owned by Royal Dutch Shell, Mitsui and Mitsubishi for $7.45 billion.", "source": "The New York Times", "multimedia": [], "headline": {"main": "Gazprom Takes Control of Sakhalin Oil Project", "kicker": "DealBook", "content_kicker": null, "print_headline": "", "name": null, "seo": null, "sub": null}, "keywords": [], "pub_date": "2007-04-19T11:28:26+0000", "document_type": "article", "news_desk": "Business", "section_name": "Business Day", "byline": {"original": "By", "person": [], "organization": null}, "type_of_material": "News", "_id": "nyt://article/021cb797-e4e3-5133-bc4d-c9b7c3324028", "word_count": 120, "uri": "nyt://article/021cb797-e4e3-5133-bc4d-c9b7c3324028"}