{"abstract": "Novocell, a stem-cell researcher, has drummed up a further $25 million in venture funding from insider investors. The latest round was led by Johnson & Johnson Development. Other insiders included Sanderling Ventures, Asset Management and Pacific Horizon Ventures.", "web_url": "https://dealbook.nytimes.com/2007/07/17/novocell-generates-25-million-in-latest-round/", "snippet": "", "lead_paragraph": "Novocell, a stem-cell researcher, has drummed up a further $25 million in venture funding from insider investors. The latest round was led by Johnson & Johnson Development. Other insiders included Sanderling Ventures, Asset Management and Pacific Horizon Ventures.", "source": "The New York Times", "multimedia": [], "headline": {"main": "Novocell Generates $25 Million in Latest Round", "kicker": "DealBook", "content_kicker": null, "print_headline": "", "name": null, "seo": null, "sub": null}, "keywords": [], "pub_date": "2007-07-17T10:24:37+0000", "document_type": "article", "news_desk": "Business", "section_name": "Business Day", "byline": {"original": "By lklaussmann", "person": [], "organization": null}, "type_of_material": "News", "_id": "nyt://article/44ec36ee-03b2-5907-8505-ee0d115e2c92", "word_count": 75, "uri": "nyt://article/44ec36ee-03b2-5907-8505-ee0d115e2c92"}