{"abstract": "Disney buys a casual gaming company for $563.2 million. Playdom is the No. 3 gaming company on Facebook.", "web_url": "https://bits.blogs.nytimes.com/2010/07/27/media-decoder-disney-buys-playdom/", "snippet": "Disney buys a casual gaming company for $563.2 million. Playdom is the No. 3 gaming company on Facebook.", "lead_paragraph": "The Walt Disney Company became Hollywood\u2019s leading player in the booming social gaming business on Tuesday with the purchase of Playdom in a deal valued at $763.2 million.", "source": "The New York Times", "multimedia": [], "headline": {"main": "Media Decoder: Disney Buys Playdom", "kicker": "Bits", "content_kicker": null, "print_headline": "", "name": null, "seo": null, "sub": null}, "keywords": [], "pub_date": "2010-07-27T20:40:41+0000", "document_type": "article", "news_desk": "Business", "section_name": "Technology", "byline": {"original": "By The New York Times", "person": [], "organization": "The New York Times"}, "type_of_material": "", "_id": "nyt://article/b41a7fbc-d8f7-5103-b991-7b45b9534dd3", "word_count": 122, "uri": "nyt://article/b41a7fbc-d8f7-5103-b991-7b45b9534dd3"}